pysurreal/__init__.py
pysurreal/connector/__init__.py
pysurreal/connector/client.py
pysurreal/connector/result.py
pysurreal/orm/__init__.py
pysurreal-1.0.0a0.dist-info/LICENSE
pysurreal-1.0.0a0.dist-info/WHEEL
pysurreal-1.0.0a0.dist-info/METADATA
pysurreal-1.0.0a0.dist-info/RECORD
