Metadata-Version: 2.1
Name: pysurreal
Version: 1.0.0a0
Summary: Community-created Python connector and ORM for SurrealDB.
Home-page: https://github.com/vcokltfre/pysurreal
License: MIT
Keywords: pysurreal,surreal,db,orm,database
Author: vcokltfre
Author-email: vcokltfre@gmail.com
Requires-Python: >=3.10,<4.0
Classifier: License :: OSI Approved :: MIT License
Classifier: Programming Language :: Python :: 3
Classifier: Programming Language :: Python :: 3.10
Requires-Dist: aiohttp (>=3.8.1,<4.0.0)
Project-URL: Repository, https://github.com/vcokltfre/pysurreal
